bizapi/__init__.py
bizapi/bizapi.py
bizapi/errors.py
bizapi/exceptions.py
bizapi/globals.py
bizapi/middleware.py
bizapi/router.py
bizapi/templating.py
bizapi/types.py
BizAPI-0.1.1.dist-info/LICENSE
BizAPI-0.1.1.dist-info/METADATA
BizAPI-0.1.1.dist-info/WHEEL
BizAPI-0.1.1.dist-info/top_level.txt
BizAPI-0.1.1.dist-info/RECORD
