Metadata-Version: 2.1
Name: BizAPI
Version: 0.1.1
Summary: It is a simple and lightweight web framework built for learning and experimentation purposes.
Home-page: https://github.com/turdibekjumabaev/oneapi
Author: Turdıbek Jumabaev
Author-email: turdibekjumabaev05@gmail.com
License: MIT
Classifier: License :: OSI Approved :: MIT License
Classifier: Programming Language :: Python
Classifier: Programming Language :: Python :: 3
Classifier: Programming Language :: Python :: 3.9
Classifier: Programming Language :: Python :: 3.10
Classifier: Programming Language :: Python :: 3.11
Classifier: Programming Language :: Python :: 3.12
Classifier: Programming Language :: Python :: Implementation :: CPython
Classifier: Programming Language :: Python :: Implementation :: PyPy
Classifier: Development Status :: 4 - Beta
Classifier: Operating System :: OS Independent
Classifier: Topic :: Internet :: WWW/HTTP :: Dynamic Content
Classifier: Topic :: Internet :: WWW/HTTP :: WSGI
Classifier: Topic :: Internet :: WWW/HTTP :: WSGI :: Application
Classifier: Topic :: Internet :: WWW/HTTP :: WSGI :: Middleware
Classifier: Intended Audience :: Developers
Requires-Python: >=3.9.0
License-File: LICENSE
Requires-Dist: WebOb ==1.8.8
Requires-Dist: parse ==1.20.2
Requires-Dist: Jinja2 ==3.1.4
Requires-Dist: whitenoise ==6.7.0
